merlion/plot.py
merlion/evaluate/anomaly.py
merlion/evaluate/base.py
merlion/evaluate/forecast.py
merlion/models/base.py
merlion/models/defaults.py
merlion/models/factory.py
merlion/models/anomaly/__init__.py
merlion/models/anomaly/autoencoder.py
merlion/models/anomaly/base.py
merlion/models/anomaly/dagmm.py
merlion/models/anomaly/dbl.py
merlion/models/anomaly/deep_point_anomaly_detector.py
merlion/models/anomaly/isolation_forest.py
merlion/models/anomaly/lstm_ed.py
merlion/models/anomaly/random_cut_forest.py
merlion/models/anomaly/spectral_residual.py
merlion/models/anomaly/stat_threshold.py
merlion/models/anomaly/utils.py
merlion/models/anomaly/vae.py
merlion/models/anomaly/windstats.py
merlion/models/anomaly/zms.py
merlion/models/anomaly/forecast_based/__init__.py
merlion/models/anomaly/forecast_based/arima.py
merlion/models/anomaly/forecast_based/base.py
merlion/models/anomaly/forecast_based/ets.py
merlion/models/anomaly/forecast_based/lstm.py
merlion/models/anomaly/forecast_based/mses.py
merlion/models/anomaly/forecast_based/prophet.py
merlion/models/anomaly/forecast_based/sarima.py
merlion/models/automl/__init__.py
merlion/models/automl/autosarima.py
merlion/models/automl/forecasting_layer_base.py
merlion/models/automl/layer_mixin.py
merlion/models/automl/seasonality_mixin.py
merlion/models/ensemble/MoE_forecast.py
merlion/models/ensemble/MoE_networks.py
merlion/models/ensemble/__init__.py
merlion/models/ensemble/anomaly.py
merlion/models/ensemble/base.py
merlion/models/ensemble/combine.py
merlion/models/ensemble/forecast.py
merlion/models/forecast/__init__.py
merlion/models/forecast/arima.py
merlion/models/forecast/autoregression_utils.py
merlion/models/forecast/baggingtrees.py
merlion/models/forecast/base.py
merlion/models/forecast/boostingtrees.py
merlion/models/forecast/ets.py
merlion/models/forecast/lstm.py
merlion/models/forecast/prophet.py
merlion/models/forecast/sarima.py
merlion/models/forecast/seq_ar_common.py
merlion/models/forecast/smoother.py
sfdc_merlion-1.0.0.dist-info/AUTHORS.md
sfdc_merlion-1.0.0.dist-info/LICENSE
sfdc_merlion-1.0.0.dist-info/METADATA
sfdc_merlion-1.0.0.dist-info/WHEEL
sfdc_merlion-1.0.0.dist-info/top_level.txt
sfdc_merlion-1.0.0.dist-info/RECORD
