Metadata-Version: 2.1
Name: sfdc-merlion
Version: 1.0.0
Summary: Merlion: A Machine Learning Framework for Time Series Intelligence
Home-page: https://github.com/salesforce/Merlion
Author: Aadyot Bhatnagar, Paul Kassianik, Chenghao Liu, Tian Lan, Wenzhuo Yang, Rowan Cassius, Doyen Sahoo, Devansh Arpit, Sri Subramanian, Gerald Woo, Amrita Saha, Arun Kumar Jagota, Gokulakrishnan Gopalakrishnan, Manpreet Singh, K C Krithika, Sukumar Maddineni, Daeki Cho, Bo Zong, Yingbo Zhou, Caiming Xiong, Silvio Savarese, Steven Hoi, Huan Wang
Author-email: abhatnagar@salesforce.com
License: 3-Clause BSD
Keywords: time series,forecasting,anomaly detection,machine learning,autoML,ensemble learning,benchmarking,Python,scientific toolkit
Platform: UNKNOWN
Requires-Python: >=3.6.0
License-File: LICENSE
License-File: AUTHORS.md
Requires-Dist: cython
Requires-Dist: dill
Requires-Dist: fbprophet
Requires-Dist: GitPython
Requires-Dist: JPype1 (==1.0.2)
Requires-Dist: matplotlib
Requires-Dist: numpy (!=1.18.*)
Requires-Dist: pandas (>=1.1.0)
Requires-Dist: pystan (<3.0")
Requires-Dist: scikit-learn (>=0.22)
Requires-Dist: scipy (>=1.5.0)
Requires-Dist: statsmodels (>=0.12.2)
Requires-Dist: torch (>=1.1.0)
Requires-Dist: lightgbm
Requires-Dist: tqdm
Requires-Dist: wheel
Requires-Dist: pytest
Provides-Extra: plot
Requires-Dist: plotly (>=4.13) ; extra == 'plot'
